pypownet/__init__.py
pypownet/agent.py
pypownet/chronic.py
pypownet/environment.py
pypownet/game.py
pypownet/grid.py
pypownet/main.py
pypownet/parameters.py
pypownet/renderer.py
pypownet/reward_signal.py
pypownet/runner.py
pypownet-2.2.9.data/data/matpower_path.config
pypownet-2.2.9.data/data/parameters/__init__.py
pypownet-2.2.9.data/data/parameters/build_new_parameters_environment.py
pypownet-2.2.9.data/data/parameters/make_reference_grid.py
pypownet-2.2.9.data/data/parameters/custom14/reward_signal.py
pypownet-2.2.9.data/data/parameters/custom14/level0/configuration.yaml
pypownet-2.2.9.data/data/parameters/custom14/level0/reference_grid.m
pypownet-2.2.9.data/data/parameters/custom14/level0/reference_grid.py
pypownet-2.2.9.data/data/parameters/custom14/level0/chronics/a/_N_datetimes.csv
pypownet-2.2.9.data/data/parameters/custom14/level0/chronics/a/_N_imaps.csv
pypownet-2.2.9.data/data/parameters/custom14/level0/chronics/a/_N_loads_p.csv
pypownet-2.2.9.data/data/parameters/custom14/level0/chronics/a/_N_loads_p_planned.csv
pypownet-2.2.9.data/data/parameters/custom14/level0/chronics/a/_N_loads_q.csv
pypownet-2.2.9.data/data/parameters/custom14/level0/chronics/a/_N_loads_q_planned.csv
pypownet-2.2.9.data/data/parameters/custom14/level0/chronics/a/_N_prods_p.csv
pypownet-2.2.9.data/data/parameters/custom14/level0/chronics/a/_N_prods_p_planned.csv
pypownet-2.2.9.data/data/parameters/custom14/level0/chronics/a/_N_prods_v.csv
pypownet-2.2.9.data/data/parameters/custom14/level0/chronics/a/_N_prods_v_planned.csv
pypownet-2.2.9.data/data/parameters/custom14/level0/chronics/a/_N_simu_ids.csv
pypownet-2.2.9.data/data/parameters/custom14/level0/chronics/a/hazards.csv
pypownet-2.2.9.data/data/parameters/custom14/level0/chronics/a/maintenance.csv
pypownet-2.2.9.data/data/parameters/custom14/level0/chronics/b/_N_datetimes.csv
pypownet-2.2.9.data/data/parameters/custom14/level0/chronics/b/_N_imaps.csv
pypownet-2.2.9.data/data/parameters/custom14/level0/chronics/b/_N_loads_p.csv
pypownet-2.2.9.dist-info/LICENSE
pypownet-2.2.9.dist-info/METADATA
pypownet-2.2.9.dist-info/WHEEL
pypownet-2.2.9.dist-info/entry_points.txt
pypownet-2.2.9.dist-info/top_level.txt
pypownet-2.2.9.dist-info/RECORD
