Metadata-Version: 2.1
Name: pypownet
Version: 2.2.9
Summary: A power network simulator with a Reinforcement Learning-focused usage.
Home-page: UNKNOWN
Author: Marvin Lerousseau
Author-email: marvin.lerousseau@gmail.com
Maintainer: Marvin Lerousseau
License: LGPLv3
Download-URL: https://github.com/marvinler/pypownet
Platform: UNKNOWN
Requires-Dist: setuptools (>=40.0.0)
Requires-Dist: matplotlib (>=2.2.2)
Requires-Dist: recommonmark (>=0.4.0)
Requires-Dist: gym (>=0.12.0)
Requires-Dist: numpy (>=1.15.0)
Requires-Dist: oct2py (>=4.0.6)
Requires-Dist: pygame (>=1.9.4)
Requires-Dist: scipy (>=1.1.0)
Requires-Dist: PYPOWER (>=5.1.4)
Requires-Dist: PyYAML (>=5.1)
Requires-Dist: pytest (>=4.4.0)
